woe_monotonic_binning/__init__.py
woe_monotonic_binning/binning.py
woe_monotonic_binning-0.5.3.dist-info/LICENSE
woe_monotonic_binning-0.5.3.dist-info/METADATA
woe_monotonic_binning-0.5.3.dist-info/WHEEL
woe_monotonic_binning-0.5.3.dist-info/top_level.txt
woe_monotonic_binning-0.5.3.dist-info/RECORD
