Metadata-Version: 2.1
Name: woe-monotonic-binning
Version: 0.5.3
Summary: Optimal binning algorithm and function to apply on a pandas DataFrame
Home-page: https://github.com/PedroHBM/woe-monotonic-binning
Download-URL: https://github.com/PedroHBM/woe-monotonic-binning/archive/v0.5.3-alpha.tar.gz
Author: PEDRO HENRIQUE BAUMGRATZ MEIRELLES
Author-email: pedrohbm@poli.ufrj.br
License: MIT
Keywords: WOE,BINNING,IV,LOGISTIC,REGRESSION
Classifier: Development Status :: 3 - Alpha
Classifier: Intended Audience :: Developers
Classifier: Intended Audience :: Science/Research
Classifier: Topic :: Software Development
Classifier: Topic :: Scientific/Engineering
Classifier: License :: OSI Approved :: MIT License
Classifier: Programming Language :: Python :: 3
Classifier: Programming Language :: Python :: 3.4
Classifier: Programming Language :: Python :: 3.5
Classifier: Programming Language :: Python :: 3.6
License-File: LICENSE
